README.md
setup.py
nba_parser/__init__.py
nba_parser/pbp.py
nba_parser/playertotals.py
nba_parser/teamtotals.py
nba_parser.egg-info/PKG-INFO
nba_parser.egg-info/SOURCES.txt
nba_parser.egg-info/dependency_links.txt
nba_parser.egg-info/requires.txt
nba_parser.egg-info/top_level.txt