Metadata-Version: 2.1
Name: nba-parser
Version: 0.2
Summary: python package to clean up ETL functions using nba_scraper output as input
Home-page: https://github.com/mcbarlowe/nba_parser
Author: Matthew Barlowe
Author-email: matt@barloweanalytics.com
License: GNU General Public License v3.0
Keywords: basketball,NBA
Platform: UNKNOWN
Classifier: Development Status :: 3 - Alpha
Classifier: Intended Audience :: Science/Research
Classifier: Topic :: Software Development :: Build Tools
Classifier: License :: OSI Approved :: GNU General Public License v3 (GPLv3)
Classifier: Programming Language :: Python :: 3.7
